awan_llm_api/__init__.py
awan_llm_api/awan.py
awan_llm_api/completions.py
awan_llm_api/utils/enums.py
awan_llm_api-0.0.1.dist-info/LICENSE
awan_llm_api-0.0.1.dist-info/METADATA
awan_llm_api-0.0.1.dist-info/WHEEL
awan_llm_api-0.0.1.dist-info/RECORD
