Metadata-Version: 2.1
Name: awan-llm-api
Version: 0.0.1
Summary: 
Author: Yohan Sambin
Requires-Python: >=3.12,<4.0
Classifier: Programming Language :: Python :: 3
Classifier: Programming Language :: Python :: 3.12
Requires-Dist: asyncio (>=3.4.3,<4.0.0)
Requires-Dist: requests (>=2.32.3,<3.0.0)
